README.rst
setup.cfg
setup.py
rpmbuild_chain/__init__.py
rpmbuild_chain/__main__.py
rpmbuild_chain/rpmbuild_chain.py
rpmbuild_chain.egg-info/PKG-INFO
rpmbuild_chain.egg-info/SOURCES.txt
rpmbuild_chain.egg-info/dependency_links.txt
rpmbuild_chain.egg-info/entry_points.txt
rpmbuild_chain.egg-info/top_level.txt