Metadata-Version: 1.1
Name: rpmbuild-chain
Version: 0.9
Summary: Build a series of SRPMs with rpmbuild
Home-page: https://github.com/jwmullally/rpmbuild-chain
Author: Joseph Mullally
Author-email: jwmullally@gmail.com
License: MIT
Platform: UNKNOWN
Classifier: Development Status :: 4 - Beta
Classifier: Intended Audience :: Developers
Classifier: Topic :: Software Development :: Build Tools
Classifier: License :: OSI Approved :: MIT License
Classifier: Programming Language :: Python :: 2
Classifier: Programming Language :: Python :: 2.7
Classifier: Programming Language :: Python :: 3
